{"type":"FeatureCollection","features":[{"_id":"574db13bdb14a11000cb4766","createdAt":"2016-05-31T15:43:55.894Z","updatedAt":"2016-10-03T12:12:21.454Z","geohash":"u12gmmnq3j7c","credibility":17,"reports":["574db13bd0e3fbe3bd5e33f0"],"attributions":["Bufo Bufo"],"sources":["Great British Public Toilet Map"],"properties":{"active":true,"access":"public","area":[{"type":"District council","name":"Norwich City Council","_id":"57f24b2587986b0010175602"}],"name":"St Andrews Car Park","type":"female and male","attended":"false","automatic":"false","notes":"Sign says that it closes at 21:00 but often seems to be open later during hours that car park is operating"},"geometry":{"type":"Point","coordinates":[1.2940317392349243,52.63110613616507]},"type":"Feature","__v":0,"distance":308.1949706795109},{"_id":"592456d4d7ffa80011a39c31","createdAt":"2017-05-23T15:35:48.327Z","updatedAt":"2017-05-23T15:35:48.327Z","geohash":"u12gmqpt90xg","credibility":18,"reports":["592456d4d0e3fbe3bd5e50c9"],"attributions":["Sophie Cabot"],"sources":["Great British Public Toilet Map"],"properties":{"active":true,"access":"public","area":[],"name":"Anglia Square Shopping Center","type":"female and male","accessibleType":"","opening":"09:00-18:00","attended":"false","babyChange":"Not Known","automatic":"false","radar":"Not Known","fee":"","notes":""},"geometry":{"type":"Point","coordinates":[1.2957537174224854,52.636445492596394]},"type":"Feature","__v":0,"distance":346.04664213104724},{"_id":"54c2347e2ec4abe957b83b7f","createdAt":"2015-01-23T11:46:06.806Z","updatedAt":"2016-10-03T16:00:45.444Z","geohash":"u12gmktjjvs8","credibility":15,"reports":["54654602115902773aab072c","5414a52e115902773aa8ff3b"],"attributions":["Rupert Redington","Open Street Map"],"sources":["Great British Public Toilet Map","http://overpass-api.de"],"properties":{"active":true,"access":"public","area":[{"type":"District council","name":"Norwich City Council","_id":"57f280ad87986b0010178f5d"}],"operator":"Norwich City Council","orig":{"id":"node/116079139","operator":"Norwich City Council","amenity":"toilets"},"automatic":"false","babyChange":"true","attended":"false","opening":"09:00-17:00","type":"female and male","name":"Norwich Market"},"geometry":{"type":"Point","coordinates":[1.2925199200000013,52.62814626000005]},"type":"Feature","__v":1,"distance":671.024989303353},{"_id":"54c2346b2ec4abe957b8357b","createdAt":"2015-01-23T11:45:47.327Z","updatedAt":"2016-10-03T13:20:57.347Z","geohash":"u12gmsu5kznr","credibility":14,"reports":["549eca28d4d356030099d187","5414a40f115902773aa8fdb8"],"attributions":["Anonymous","Open Street Map"],"sources":["Great British Public Toilet Map","http://overpass-api.de"],"properties":{"active":true,"access":"public","area":[{"type":"District council","name":"Norwich City Council","_id":"57f25b3987986b0010176735"}],"orig":{"id":"node/472647140","amenity":"toilets"},"type":"male urinal"},"geometry":{"type":"Point","coordinates":[1.3020923,52.62922830000006]},"type":"Feature","__v":1,"distance":673.146455442342},{"_id":"54c234b72ec4abe957b8473e","createdAt":"2015-01-23T11:47:03.102Z","updatedAt":"2016-10-03T12:00:21.324Z","geohash":"u12gmkx8cyjv","credibility":15,"reports":["5414a40d115902773aa8fdb2","55bcea91d0e3fbe3bd5e3076"],"attributions":["Open Street Map","Gail Ramster"],"sources":["http://overpass-api.de","Great British Public Toilet Map"],"properties":{"active":true,"access":"public","area":[{"type":"District council","name":"Norwich City Council","_id":"57f2485587986b0010175304"}],"orig":{"id":"node/1230743522","level":"2.5","layer":"-2","amenity":"toilets"},"name":"Castle Mall level 2","accessibleType":"unisex","babyChange":"true","automatic":"false","fee":"Free"},"geometry":{"type":"Point","coordinates":[1.2957831,52.6274202]},"type":"Feature","__v":2,"distance":714.244441575797}]}